genominterv/__init__.py
genominterv/chrom_sizes.py
genominterv-1.1.dist-info/LICENSE
genominterv-1.1.dist-info/METADATA
genominterv-1.1.dist-info/WHEEL
genominterv-1.1.dist-info/top_level.txt
genominterv-1.1.dist-info/RECORD
